pydantic_errors_messages_translations/__init__.py
pydantic_errors_messages_translations/helpers.py
pydantic_errors_messages_translations/translations.py
pydantic_errors_messages_translations-1.1.1.dist-info/METADATA
pydantic_errors_messages_translations-1.1.1.dist-info/WHEEL
pydantic_errors_messages_translations-1.1.1.dist-info/top_level.txt
pydantic_errors_messages_translations-1.1.1.dist-info/RECORD
