Metadata-Version: 2.1
Name: pydantic-errors-messages-translations
Version: 1.1.1
Summary: It's a collection of translations for pydantic errors in any languages
Home-page: https://github.com/fabriciomsdev/pydantic-errors-messages-translation
Author: Fabricio Magalhães Sena
Author-email: fabricioms.dev@gmail.com
License: MIT
Platform: UNKNOWN
Classifier: License :: OSI Approved :: MIT License
Classifier: Programming Language :: Python :: 3
Classifier: Programming Language :: Python :: 3.7
Requires-Dist: pydantic
Requires-Dist: pydantic-i18n
